pyflink/serializers.py
pyflink/find_flink_home.py
pyflink/__init__.py
pyflink/version.py
pyflink/java_gateway.py
pyflink/README.txt
pyflink/gen_protos.py
pyflink/pyflink_gateway_server.py
pyflink/pyflink_callback_server.py
pyflink/shell.py
pyflink/util/__init__.py
pyflink/util/java_utils.py
pyflink/util/exceptions.py
pyflink/fn_execution/state_impl.py
pyflink/fn_execution/coders.py
pyflink/fn_execution/ResettableIO.py
pyflink/fn_execution/__init__.py
pyflink/fn_execution/pickle.py
pyflink/fn_execution/profiler.py
pyflink/fn_execution/coder_impl_fast.pxd
pyflink/fn_execution/stream_fast.c
pyflink/fn_execution/coder_impl_fast.c
pyflink/fn_execution/stream_fast.pyx
pyflink/fn_execution/stream_fast.pxd
pyflink/fn_execution/coder_impl_fast.cpython-311-x86_64-linux-gnu.so
pyflink/fn_execution/coder_impl_fast.pyx
pyflink/fn_execution/internal_state.py
pyflink/fn_execution/coder_impl_slow.py
pyflink/fn_execution/flink_fn_execution_pb2.py
pyflink/fn_execution/flink_fn_execution_pb2.pyi
pyflink/fn_execution/stream_fast.cpython-311-x86_64-linux-gnu.so
pyflink/fn_execution/stream_slow.py
pyflink/fn_execution/formats/__init__.py
pyflink/fn_execution/formats/avro.py
pyflink/fn_execution/metrics/__init__.py
pyflink/fn_execution/metrics/process/distribution_impl.py
pyflink/fn_execution/metrics/process/counter_impl.py
pyflink/fn_execution/metrics/process/__init__.py
pyflink/fn_execution/metrics/process/metric_impl.py
pyflink/fn_execution/metrics/process/meter_impl.py
pyflink/fn_execution/metrics/embedded/distribution_impl.py
pyflink/fn_execution/metrics/embedded/counter_impl.py
pyflink/fn_execution/metrics/embedded/__init__.py
pyflink/fn_execution/metrics/embedded/metric_impl.py
pyflink/fn_execution/metrics/embedded/meter_impl.py
pyflink/fn_execution/utils/__init__.py
pyflink/fn_execution/utils/operation_utils.py
pyflink/fn_execution/beam/beam_coder_impl_fast.cpython-311-x86_64-linux-gnu.so
cp_pyflink-2.0.dev0.dist-info/RECORD
cp_pyflink-2.0.dev0.dist-info/METADATA
cp_pyflink-2.0.dev0.dist-info/WHEEL
cp_pyflink-2.0.dev0.dist-info/top_level.txt
cp_pyflink-2.0.dev0.dist-info/licenses/LICENSE
