Metadata-Version: 2.4
Name: cp-pyflink
Version: 2.0.dev0
Summary: Apache Flink Python API
Home-page: https://flink.apache.org
Author: Apache Software Foundation
Author-email: dev@flink.apache.org
License: https://www.apache.org/licenses/LICENSE-2.0
Classifier: Development Status :: 5 - Production/Stable
Classifier: License :: OSI Approved :: Apache Software License
Classifier: Programming Language :: Python :: 3.8
Classifier: Programming Language :: Python :: 3.9
Classifier: Programming Language :: Python :: 3.10
Classifier: Programming Language :: Python :: 3.11
Requires-Python: >=3.8
License-File: LICENSE
Requires-Dist: py4j==0.10.9.7
Requires-Dist: python-dateutil<3,>=2.8.0
Requires-Dist: apache-beam<=2.61.0,>=2.54.0
Requires-Dist: cloudpickle>=2.2.0
Requires-Dist: avro>=1.12.0
Requires-Dist: pytz>=2018.3
Requires-Dist: fastavro!=1.8.0,>=1.1.0
Requires-Dist: requests>=2.26.0
Requires-Dist: protobuf>=3.19.0
Requires-Dist: numpy>=1.22.4
Requires-Dist: pandas>=1.3.0
Requires-Dist: pyarrow>=5.0.0
Requires-Dist: pemja==0.4.1; platform_system != "Windows"
Requires-Dist: httplib2>=0.19.0
Requires-Dist: ruamel.yaml>=0.18.4
Requires-Dist: cp-pyflink-libraries==2.0.dev0
Dynamic: author
Dynamic: author-email
Dynamic: classifier
Dynamic: description
Dynamic: description-content-type
Dynamic: home-page
Dynamic: license
Dynamic: license-file
Dynamic: requires-dist
Dynamic: requires-python
Dynamic: summary
